{"sha256": "228de7cff29cfc3148706c32cb1463f7bef1e080402d771f37571c395aa03fbe", "virustotal": {"permalink": "http://www.virustotal.com/file/228de7cff29cfc3148706c32cb1463f7bef1e080402d771f37571c395aa03fbe/analysis/", "scan_date": "2012-08-30 16:00:43", "positives": 3, "total": 42, "scans": {"TotalDefense": {"result": null}, "CAT-QuickHeal": {"result": null}, "AhnLab-V3": {"result": null}, "Comodo": {"result": "UnclassifiedMalware"}, "TheHacker": {"result": null}, "F-Prot": {"result": null}, "Fortinet": {"result": null}, "TrendMicro-HouseCall": {"result": null}, "SUPERAntiSpyware": {"result": null}, "VIPRE": {"result": null}, "VBA32": {"result": null}, "BitDefender": {"result": null}, "TrendMicro": {"result": null}, "DrWeb": {"result": "Adware.Izp.origin"}, "ByteHero": {"result": null}, "Symantec": {"result": null}, "Antiy-AVL": {"result": null}, "nProtect": {"result": null}, "Norman": {"result": null}, "McAfee": {"result": null}, "Emsisoft": {"result": null}, "ClamAV": {"result": null}, "F-Secure": {"result": null}, "Avast": {"result": null}, "ViRobot": {"result": null}, "Microsoft": {"result": null}, "K7AntiVirus": {"result": null}, "Kaspersky": {"result": null}, "GData": {"result": null}, "Ikarus": {"result": null}, "Sophos": {"result": null}, "AntiVir": {"result": null}, "Commtouch": {"result": null}, "AVG": {"result": null}, "PCTools": {"result": null}, "ESET-NOD32": {"result": "a variant of Android/Adware.Izp.A"}, "Jiangmin": {"result": null}, "VirusBuster": {"result": null}, "McAfee-GW-Edition": {"result": null}, "eSafe": {"result": null}, "Rising": {"result": null}, "Panda": {"result": null}}}, "added_timestamp": "2012-12-29T11:19:28+00:00", "sha512": "53d65fdebb2a21547d4672d8ae4f1d58a6406cc36e06609f33098100095e392b043beb76358bc2ceb63522130e24f49c61300aba200dced8d775e26052100f3c", "ssdeep": "24576:l8npTXTYNvDIV11xb4bnLyyLiuPqH4/kTB4:+XTYMT/6mW5PqY8q", "filetype": "Java archive data (JAR)", "sha384": "f05685204a08a4b431529c35a14de8f1235965e184c3e45692429d3bf47c2dba4e925d342890124c5c43088eb2df9a3f", "trid": {"0": "Android Package (73.9%)", "1": "Java Archive (20.4%)", "2": "ZIP compressed archive (5.6%)"}, "exif": {"FileSize": "832 kB", "FileType": "ZIP", "FileTypeExtension": "zip", "MIMEType": "application/zip", "ZipBitFlag": "0x0008", "ZipCRC": "0x7f55eff8", "ZipCompressedSize": 169, "ZipCompression": "Deflated", "ZipFileName": "assets/1.html", "ZipModifyDate": "2012:08:03 19:20:24", "ZipRequiredVersion": 20, "ZipUncompressedSize": 230}, "size": 852256, "extension": "apk", "md5": "078b15fd961c292bb1bb81db43db2f63", "sha224": "8f3392eaae0702cb1fbe356fe9f44ad70e3a9c4027c0915e7604340c", "mimetype": "application/java-archive", "sha1": "01b08d8903c37e70673de6a7a7a5e0c2a313a4de", "response": 1}