{"sha256": "54521883eb10ef2dc0ef48d944ae88e5976628201961205adc90a9be88d77d38", "virustotal": {"permalink": "http://www.virustotal.com/file/54521883eb10ef2dc0ef48d944ae88e5976628201961205adc90a9be88d77d38/analysis/", "scan_date": "2012-07-26 12:04:40", "positives": 20, "total": 41, "scans": {"TotalDefense": {"result": null}, "CAT-QuickHeal": {"result": "Android.Opfake.S299"}, "AhnLab-V3": {"result": null}, "Comodo": {"result": "UnclassifiedMalware"}, "TheHacker": {"result": null}, "F-Prot": {"result": null}, "Fortinet": {"result": "Android/OpFake.C"}, "TrendMicro-HouseCall": {"result": "AndroidOS_FAKE.BLK"}, "SUPERAntiSpyware": {"result": null}, "VBA32": {"result": "Trojan-SMS.AndroidOS.Opfake.a"}, "BitDefender": {"result": "Android.Trojan.FakeInst.AN"}, "TrendMicro": {"result": "AndroidOS_FAKE.BLK"}, "DrWeb": {"result": "Android.SmsSend.358.origin"}, "ByteHero": {"result": null}, "Symantec": {"result": null}, "Antiy-AVL": {"result": "Trojan/AndroidOS.Opfake"}, "nProtect": {"result": null}, "Norman": {"result": null}, "McAfee": {"result": null}, "Emsisoft": {"result": "AndroidOS.FakeInst.AT!IK"}, "ClamAV": {"result": null}, "F-Secure": {"result": "Trojan:Android/OpFake.C"}, "Avast": {"result": "Android:OpFake-S [Trj]"}, "ViRobot": {"result": null}, "Microsoft": {"result": null}, "K7AntiVirus": {"result": null}, "Kaspersky": {"result": "HEUR:Trojan-SMS.AndroidOS.Opfake.a"}, "GData": {"result": "Android.Trojan.FakeInst.AN"}, "Ikarus": {"result": "AndroidOS.FakeInst.AT"}, "Sophos": {"result": "Andr/Opfake-C"}, "AntiVir": {"result": "Android/SMSSend.A"}, "Commtouch": {"result": null}, "AVG": {"result": null}, "VIPRE": {"result": "Trojan.AndroidOS.OpFake.c (v)"}, "ESET-NOD32": {"result": "Android/TrojanSMS.Agent.BG"}, "Jiangmin": {"result": "Trojan/AndroidOS.agc"}, "VirusBuster": {"result": null}, "McAfee-GW-Edition": {"result": null}, "eSafe": {"result": null}, "Rising": {"result": null}, "Panda": {"result": null}}}, "added_timestamp": "2012-11-16T23:03:07+00:00", "sha224": "16ed6d661a923bf025dbf4a552fd99c976b3fcdf0be9d69537a5628d", "trid": {"0": "Android Package (73.9%)", "1": "Java Archive (20.4%)", "2": "ZIP compressed archive (5.6%)"}, "sha1": "7ec1af2cec4b7e93b83915316cfd15391b7143dd", "filetype": "Zip archive data, at least v2.0 to extract", "md5": "087357326784247edcf3b392ac53d290", "mimetype": "application/zip", "extension": "apk", "exif": {"FileSize": "53 kB", "FileType": "ZIP", "FileTypeExtension": "zip", "MIMEType": "application/zip", "ZipBitFlag": "0x0008", "ZipCRC": "0xa02692c4", "ZipCompressedSize": 601, "ZipCompression": "Deflated", "ZipFileName": "META-INF/MANIFEST.MF", "ZipModifyDate": "2012:03:17 19:05:06", "ZipRequiredVersion": 20, "ZipUncompressedSize": 1209}, "sha512": "624192b001f2f541dce10c24db9b51c779e5b9597ff1acd131181e87cbca7eed36a576988757df1ae366abc09ef4dda8d1ec7289a6ee1317d6f6e994587b1b8b", "sha384": "821a4983a5085104957fb5b26ba19d7a56088bd387d0897418cceac0ef14c3bbdc994a81e3ae78b9a3fabcffa04c4a4e", "ssdeep": "1536:1jG/rWuAlqAZTCEobeci9RYZChiYTFIxA66:1jOrWbAETBobnlyZ", "size": 54006, "response": 1}