{"sha256": "3031bc337ef84de192362cea82bd0a10cecbfd6cc6ba7bd00fff50122bb2573d", "virustotal": {"permalink": "http://www.virustotal.com/file/3031bc337ef84de192362cea82bd0a10cecbfd6cc6ba7bd00fff50122bb2573d/analysis/", "scan_date": "2012-08-22 18:20:48", "positives": 25, "total": 41, "scans": {"TotalDefense": {"result": null}, "CAT-QuickHeal": {"result": "Android.BoxerSms.B"}, "AhnLab-V3": {"result": null}, "Comodo": {"result": "UnclassifiedMalware"}, "TheHacker": {"result": null}, "F-Prot": {"result": "ANDR/FakeInst.F"}, "Fortinet": {"result": "Riskware/FakeInst!Android"}, "TrendMicro-HouseCall": {"result": "AndroidOS_BOXER.DY"}, "SUPERAntiSpyware": {"result": null}, "VBA32": {"result": "Trojan-SMS.AndroidOS.FakeInst.a"}, "BitDefender": {"result": "Android.Trojan.FakeInst.D"}, "TrendMicro": {"result": "AndroidOS_BOXER.DY"}, "DrWeb": {"result": "Android.SmsSend.401"}, "ByteHero": {"result": null}, "Symantec": {"result": "Android.Fakemini"}, "Antiy-AVL": {"result": "Trojan/win32.agent"}, "nProtect": {"result": null}, "Norman": {"result": null}, "McAfee": {"result": null}, "Emsisoft": {"result": "Trojan.AndroidOS.FakeInst!IK"}, "ClamAV": {"result": null}, "F-Secure": {"result": "Trojan:Android/Fakeinst.E"}, "Avast": {"result": "Android:FakeBrows-A [Trj]"}, "Microsoft": {"result": "Program:AndroidOS/BoxerSms.B"}, "Commtouch": {"result": "ANDR/FakeInst.F"}, "K7AntiVirus": {"result": "Riskware"}, "Kaspersky": {"result": "HEUR:Trojan-SMS.AndroidOS.FakeInst.a"}, "ViRobot": {"result": null}, "GData": {"result": "Android.Trojan.FakeInst.D"}, "Ikarus": {"result": "Trojan.AndroidOS.FakeInst"}, "Sophos": {"result": "Andr/Boxer-C"}, "AntiVir": {"result": "Android/FakeInst.A"}, "AVG": {"result": null}, "VIPRE": {"result": "Trojan.AndroidOS.FakeInst.d (v)"}, "ESET-NOD32": {"result": "Android/TrojanSMS.FakeInst.D"}, "Jiangmin": {"result": "Trojan/AndroidOS.cos"}, "VirusBuster": {"result": null}, "McAfee-GW-Edition": {"result": null}, "eSafe": {"result": null}, "Rising": {"result": null}, "Panda": {"result": null}}}, "added_timestamp": "2012-11-27T21:54:02+00:00", "sha1": "efbbc05ff931105f9b81552ce051ffbbc4a7c08f", "sha384": "b5572246acd6e261510d41be6272f6e63af25f5387eb580f5d60cd52288b8110179458bdc00d5480c4a9e52e2dedf48d", "sha512": "93758ab07c8534fd9befd38e273115e430633db29234d1a0b9352acc3f342fb7ecbd38442652441c4fe9cad86bd606217018abbc387d7f3e4e33f79efbc5d118", "extension": "apk", "mimetype": "application/zip", "filetype": "Zip archive data, at least v2.0 to extract", "trid": {"0": "Android Package (73.9%)", "1": "Java Archive (20.4%)", "2": "ZIP compressed archive (5.6%)"}, "size": 63806, "sha224": "eab46cc06aef20790b50bdd992b8b0ca9b7d9b435706081844192097", "md5": "1a5be173810a81671be218763c002e97", "exif": {"FileSize": "62 kB", "FileType": "ZIP", "FileTypeExtension": "zip", "MIMEType": "application/zip", "ZipBitFlag": "0x0008", "ZipCRC": "0x9d95d0d3", "ZipCompressedSize": 809, "ZipCompression": "Deflated", "ZipFileName": "META-INF/MANIFEST.MF", "ZipModifyDate": "2012:05:02 15:06:02", "ZipRequiredVersion": 20, "ZipUncompressedSize": 2154}, "ssdeep": "1536:Y2YY0QRtRzC6KcqFckJojGEfdaKvH1UevgYGA5B3X:4QxKcdzjGE1a8g9kBn", "response": 1}