{"sha256": "06c8feb5b92ca21e27e0024c38074963fe0c83e580886eadeb738c6d79f80bd3", "virustotal": {"permalink": "http://www.virustotal.com/file/06c8feb5b92ca21e27e0024c38074963fe0c83e580886eadeb738c6d79f80bd3/analysis/", "scan_date": "2012-08-21 03:09:27", "positives": 23, "total": 39, "scans": {"TotalDefense": {"result": null}, "CAT-QuickHeal": {"result": "Android.BoxerSms.D"}, "Comodo": {"result": "UnclassifiedMalware"}, "TrendMicro-HouseCall": {"result": "AndroidOS_BOXERSMS.NM"}, "TheHacker": {"result": null}, "F-Prot": {"result": "ANDR/FakeInst.L"}, "Fortinet": {"result": "Riskware/FakeInst!Android"}, "Microsoft": {"result": "Program:AndroidOS/BoxerSms.D"}, "SUPERAntiSpyware": {"result": null}, "VIPRE": {"result": "Trojan.AndroidOS.Boxer.d (v)"}, "VBA32": {"result": null}, "TrendMicro": {"result": "AndroidOS_BOXERSMS.NM"}, "DrWeb": {"result": "Android.SmsSend.395"}, "ESET-NOD32": {"result": "Android/TrojanSMS.Boxer.BF"}, "BitDefender": {"result": "Android.Trojan.FakeInst.AS"}, "Antiy-AVL": {"result": "Trojan/AndroidOS.FakeInst"}, "nProtect": {"result": null}, "Norman": {"result": null}, "McAfee": {"result": null}, "Emsisoft": {"result": "Trojan.AndroidOS.BoxerSms!IK"}, "ClamAV": {"result": null}, "F-Secure": {"result": "Trojan:Android/Boxer.C"}, "Avast": {"result": "Android:FakeInst-AB [Trj]"}, "ViRobot": {"result": null}, "Commtouch": {"result": "ANDR/FakeInst.L"}, "K7AntiVirus": {"result": "Riskware"}, "Kaspersky": {"result": "HEUR:Trojan-SMS.AndroidOS.FakeInst.a"}, "GData": {"result": "Android.Trojan.FakeInst.AS"}, "Ikarus": {"result": "Trojan.AndroidOS.BoxerSms"}, "Sophos": {"result": "Andr/Boxer-D"}, "AntiVir": {"result": "Android/BoxerSms.D"}, "AVG": {"result": null}, "PCTools": {"result": null}, "Jiangmin": {"result": "Trojan/AndroidOS.bvu"}, "VirusBuster": {"result": null}, "McAfee-GW-Edition": {"result": null}, "eSafe": {"result": null}, "Rising": {"result": null}, "Panda": {"result": null}}}, "added_timestamp": "2012-11-26T22:55:25+00:00", "size": 93121, "ssdeep": "1536:3+WYjz/cJTP5luY0YvlfuY0Yvl7uY0Yvl4uY0YvlCkyhnEB7XX2amx4+sGacmi16:3+WYjz/cZPbyYtfyYt7yYt4yYtCkytEL", "filetype": "Zip archive data, at least v2.0 to extract", "sha224": "a2763be3ca6a5acfb794f3eb4afd8b446b41337697a498cca032199b", "extension": "apk", "md5": "235bf50e0a59675a773f8356f1a823cd", "trid": {"0": "Android Package (73.9%)", "1": "Java Archive (20.4%)", "2": "ZIP compressed archive (5.6%)"}, "sha1": "ee0549bff1482b373d6e522e362412d010dd2ef8", "sha384": "e0eb97ccc5cd9d7f5b84ada7e9434742e4059da45fa4ffd8cf48e6d8806eebbb87651f4064ebbdc53dca28b5c5c2230d", "exif": {"FileSize": "91 kB", "FileType": "ZIP", "FileTypeExtension": "zip", "MIMEType": "application/zip", "ZipBitFlag": "0x0808", "ZipCRC": "0xd2d9446f", "ZipCompressedSize": 875, "ZipCompression": "Deflated", "ZipFileName": "META-INF/MANIFEST.MF", "ZipModifyDate": "2012:05:25 08:42:17", "ZipRequiredVersion": 20, "ZipUncompressedSize": 2121}, "mimetype": "application/zip", "sha512": "35f72f03da4dbf7001865a43890be457fe1ccbf226b81a8ac090ea51957549e13527c84652ff238099cfb66e3b5eddef40915fb19429ec0a9a2a721f37321a82", "response": 1}