{"sha256": "82cd0efe0953bd93b492cd1a9a7148b7fd8a1a7131d09d8086adc08e9213e9e6", "virustotal": {"permalink": "http://www.virustotal.com/file/82cd0efe0953bd93b492cd1a9a7148b7fd8a1a7131d09d8086adc08e9213e9e6/analysis/", "scan_date": "2012-07-29 11:15:19", "positives": 21, "total": 40, "scans": {"TotalDefense": {"result": ""}, "CAT-QuickHeal": {"result": "Android.FakeInst.C"}, "AhnLab-V3": {"result": ""}, "Comodo": {"result": "UnclassifiedMalware"}, "TheHacker": {"result": ""}, "F-Prot": {"result": ""}, "Fortinet": {"result": "Riskware/FakeInst!Android"}, "Microsoft": {"result": "Trojan:AndroidOS/FakeInstSms.A"}, "SUPERAntiSpyware": {"result": ""}, "VBA32": {"result": "Trojan-SMS.AndroidOS.FakeInst.a"}, "BitDefender": {"result": "Android.Trojan.FakeInst.N"}, "TrendMicro": {"result": "AndroidOS_FAKE.MC"}, "DrWeb": {"result": "Android.SmsSend.286.origin"}, "ESET-NOD32": {"result": "Android/TrojanSMS.FakeInst.K"}, "Symantec": {"result": "Android.Premiumtext"}, "Antiy-AVL": {"result": "Trojan/win32.agent"}, "nProtect": {"result": ""}, "Norman": {"result": ""}, "McAfee": {"result": ""}, "Emsisoft": {"result": "AndroidOS.FakeInst!IK"}, "ClamAV": {"result": ""}, "F-Secure": {"result": "Trojan:Android/SMStado.A!mfb"}, "Avast": {"result": "Android:FakeInst-Q [Trj]"}, "TrendMicro-HouseCall": {"result": "AndroidOS_FAKE.MC"}, "Commtouch": {"result": ""}, "K7AntiVirus": {"result": ""}, "Kaspersky": {"result": "HEUR:Trojan-SMS.AndroidOS.FakeInst.a"}, "ViRobot": {"result": ""}, "GData": {"result": "Android.Trojan.FakeInst.N"}, "Ikarus": {"result": "AndroidOS.FakeInst"}, "Sophos": {"result": "Andr/FakeIns-E"}, "AntiVir": {"result": "Android/Fake.A"}, "AVG": {"result": ""}, "VIPRE": {"result": ""}, "Jiangmin": {"result": "Trojan/AndroidOS.aua"}, "VirusBuster": {"result": ""}, "McAfee-GW-Edition": {"result": ""}, "eSafe": {"result": ""}, "Rising": {"result": ""}, "Panda": {"result": ""}}}, "added_timestamp": "2012-11-24T09:41:04+00:00", "sha384": "1b1e94c21e84e77221279f54f76601bc9e67ee3581bee6cdfdca1845616b2c6a2184dd4df3d5477177ed23b13ace2564", "md5": "292f5c20c6a752b15f3d9309de2b8cf4", "sha1": "7502dc28da6f6b442321367b590d756a92ac669d", "ssdeep": "768:4cFnnZIAbnDCbxRaA+PektA+PYmH9A+PUcoif8+Gseom+LG5iCzgTCUiCzgTCriC:4c/Ks2kzAoj8N+GshG5iHTjiHTMiHTm", "sha224": "6fda7105fcb92393f79ee3d9c0504c27413c0ac79ffa7bb3de7f644b", "mimetype": "application/zip", "exif": {"FileSize": "56 kB", "FileType": "ZIP", "FileTypeExtension": "zip", "MIMEType": "application/zip", "ZipBitFlag": "0x0008", "ZipCRC": "0xac137702", "ZipCompressedSize": 647, "ZipCompression": "Deflated", "ZipFileName": "META-INF/MANIFEST.MF", "ZipModifyDate": "2012:01:26 11:48:07", "ZipRequiredVersion": 20, "ZipUncompressedSize": 1589}, "extension": "apk", "trid": {"0": "Android Package (73.9%)", "1": "Java Archive (20.4%)", "2": "ZIP compressed archive (5.6%)"}, "sha512": "96e2ccf82ac26b2cf1a5c4b6ddbdd0673a89369803829fb02aa1d3f5525dfcdce3ff096c788cdad3d50363942b6687ea8cb125394f7949f1417d33e53722931c", "size": 57371, "filetype": "Zip archive data, at least v2.0 to extract", "response": 1}