{"sha256": "126a6ad8d72f70844499b4c7eedc086cc2280a7e53fa144762a7ef67e0b72a04", "sha1": "26807803b776741dbd36910358e32afc8e534a12", "ssdeep": "3072:bqWfV/kmF0ldh0CyleFBCyleFKCyleFjCyleFnCyleF8CyleFr:b37IdyCzBCzKCzjCznCz8Czr", "sha224": "0f92db474fba79588ca262b5a1b42b29ee5e6fa24914006d5ce51d43", "size": 114586, "trid": {"0": "Android Package (73.9%)", "1": "Java Archive (20.4%)", "2": "ZIP compressed archive (5.6%)"}, "exif": {"FileSize": "112 kB", "FileType": "ZIP", "FileTypeExtension": "zip", "MIMEType": "application/zip", "ZipBitFlag": "0x0008", "ZipCRC": "0xba690c18", "ZipCompressedSize": 502, "ZipCompression": "Deflated", "ZipFileName": "META-INF/MANIFEST.MF", "ZipModifyDate": "2012:01:11 21:15:19", "ZipRequiredVersion": 20, "ZipUncompressedSize": 1241}, "sha512": "8a0a24d6b87d8b419cf8e37d62012492a0c8c67b69dc77035d10569bf34b2d361b821ba466d2034382772be6b373f81b494dee80e19f944de3c24928fe65a74c", "sha384": "f7f5fa8912cf4c24b021c0b727a1d397bbc00e22717bf2a894bc63166a4906a2567c257e7ea103ecc62cc1277b1c0470", "filetype": "Zip archive data, at least v2.0 to extract", "md5": "4cc92585e0b6141d7357e6a38d73f635", "extension": "apk", "mimetype": "application/zip", "virustotal": {"permalink": "http://www.virustotal.com/file/126a6ad8d72f70844499b4c7eedc086cc2280a7e53fa144762a7ef67e0b72a04/analysis/", "scan_date": "2012-10-21 12:30:14", "positives": 35, "total": 44, "scans": {"TotalDefense": {"result": "AndroidOS/Opfake.A!generic"}, "CAT-QuickHeal": {"result": "Android.FakeNotify.A"}, "AhnLab-V3": {"result": ""}, "MicroWorld-eScan": {"result": "Android.Trojan.FakeInst.L"}, "F-Prot": {"result": "ANDR/FakeInst.AJ"}, "Fortinet": {"result": "Android/FakeNotify.A!tr.dial"}, "ViRobot": {"result": ""}, "SUPERAntiSpyware": {"result": ""}, "ESET-NOD32": {"result": "Android/TrojanSMS.Agent.V"}, "BitDefender": {"result": "Android.Trojan.FakeInst.L"}, "Antiy-AVL": {"result": "Trojan/AndroidOS.Opfake"}, "AntiVir": {"result": "Android/Agent.20399.4"}, "Emsisoft": {"result": "Android.Trojan.FakeInst.L (B)"}, "eSafe": {"result": ""}, "Sophos": {"result": "Andr/FakeNtfy-A"}, "McAfee": {"result": "Generic-FABC!4CC92585E0B6"}, "AVG": {"result": "Android_dc.AMV"}, "nProtect": {"result": ""}, "Jiangmin": {"result": "Trojan/AndroidOS.jj"}, "PCTools": {"result": "Android.Fakenotify"}, "Comodo": {"result": "UnclassifiedMalware"}, "McAfee-GW-Edition": {"result": "Artemis!4CC92585E0B6"}, "Agnitum": {"result": "Trojan.AndroidOS.FakeNotify.A"}, "TrendMicro": {"result": "AndroidOS_FAKENOTIFY.A"}, "DrWeb": {"result": "Android.SmsSend.281.origin"}, "ByteHero": {"result": ""}, "Symantec": {"result": "Trojan.Gen.2"}, "VIPRE": {"result": "Trojan.AndroidOS.FakeNotify.a (v)"}, "Norman": {"result": "FakeNotify.A"}, "ClamAV": {"result": "Android.FakeAV-2"}, "F-Secure": {"result": "Trojan:Android/FakeNotify.A"}, "Avast": {"result": "Android:FakeNotify-A [Trj]"}, "Kingsoft": {"result": "Android.Troj.Opfake.a.(kcloud)"}, "TrendMicro-HouseCall": {"result": "AndroidOS_FAKENOTIFY.A"}, "Commtouch": {"result": "ANDR/FakeInst.AJ"}, "K7AntiVirus": {"result": "Riskware"}, "Kaspersky": {"result": "HEUR:Trojan-SMS.AndroidOS.Opfake.bo"}, "GData": {"result": "Android.Trojan.FakeInst.L"}, "Ikarus": {"result": "Trojan.AndroidOS.FakeNotify"}, "Microsoft": {"result": "Trojan:AndroidOS/FakeNotify.A"}, "VBA32": {"result": "Trojan-SMS.AndroidOS.Opfake.bo"}, "TheHacker": {"result": ""}, "Rising": {"result": ""}, "Panda": {"result": ""}}}, "added_timestamp": "2012-11-02T04:34:58+00:00", "response": 1}