{"sha256": "df3c4cbe2b41398bf8e1e807f5ca1b8a6ca2ebe3f1686f95bc36ea83bbea694e", "virustotal": {"permalink": "http://www.virustotal.com/file/df3c4cbe2b41398bf8e1e807f5ca1b8a6ca2ebe3f1686f95bc36ea83bbea694e/analysis/", "scan_date": "2012-11-19 10:20:37", "positives": 3, "total": 44, "scans": {"TotalDefense": {"result": null}, "CAT-QuickHeal": {"result": null}, "AhnLab-V3": {"result": null}, "MicroWorld-eScan": {"result": null}, "F-Prot": {"result": null}, "Fortinet": {"result": null}, "ViRobot": {"result": null}, "SUPERAntiSpyware": {"result": null}, "ESET-NOD32": {"result": null}, "BitDefender": {"result": null}, "Antiy-AVL": {"result": null}, "AntiVir": {"result": null}, "Emsisoft": {"result": null}, "eSafe": {"result": null}, "Sophos": {"result": null}, "McAfee": {"result": null}, "AVG": {"result": "Android_dc.DCY"}, "nProtect": {"result": null}, "Jiangmin": {"result": null}, "PCTools": {"result": null}, "Comodo": {"result": null}, "McAfee-GW-Edition": {"result": null}, "Agnitum": {"result": null}, "TrendMicro": {"result": null}, "DrWeb": {"result": "Tool.Rooter.10.origin"}, "ByteHero": {"result": null}, "Symantec": {"result": null}, "VIPRE": {"result": null}, "Norman": {"result": null}, "ClamAV": {"result": null}, "F-Secure": {"result": null}, "Avast": {"result": null}, "Kingsoft": {"result": null}, "TrendMicro-HouseCall": {"result": null}, "Commtouch": {"result": null}, "K7AntiVirus": {"result": null}, "Kaspersky": {"result": null}, "GData": {"result": null}, "Ikarus": {"result": "Virus.Android_mc"}, "Microsoft": {"result": null}, "VBA32": {"result": null}, "TheHacker": {"result": null}, "Rising": {"result": null}, "Panda": {"result": null}}}, "added_timestamp": "2012-11-19T06:08:08+00:00", "extension": "apk", "trid": {"0": "Android Package (73.9%)", "1": "Java Archive (20.4%)", "2": "ZIP compressed archive (5.6%)"}, "mimetype": "application/java-archive", "sha512": "66014107235633919b12ec22437d95651b9f00ea6a0eee5e90ee957b6a4e12b05cecd6a217d4b92e206d8e38442a9e10a754c4275a50fcf19c984b41edaf32f9", "md5": "4ec9e96986478cb000f9d58f374f39f5", "sha384": "38a99f0c9bd6379709efcced3a9c3e9d8ecc69410988341afba4f34c16483cee1ca236fb6fe0d961f2265ca64292416e", "exif": {"FileSize": "192 kB", "FileType": "ZIP", "FileTypeExtension": "zip", "MIMEType": "application/zip", "ZipBitFlag": 0, "ZipCRC": "0x27d519a9", "ZipCompressedSize": 153, "ZipCompression": "None", "ZipFileName": "res/drawable/dark_header.9.png", "ZipModifyDate": "2010:09:05 15:46:28", "ZipRequiredVersion": 10, "ZipUncompressedSize": 153}, "sha224": "8ba92c7a5de3814860904d717271fd017133fa9395d7ebac5632cb6a", "filetype": "Java archive data (JAR)", "size": 196521, "ssdeep": "3072:ysF8CMXMGIIFzrdQ5023X9phSTt6rUKaJ/O4OroXB2Nda6B5Hpb2/:dFsXoIxrdQ502JUpNTOsxgBpc/", "sha1": "7479e11f4df198c743bd430ef54f94999690c73b", "response": 1}