{"sha256": "1680fd004bfdda3fcf2792d8b7894dae605af008647693760fa3fdfa3677974c", "md5": "529a349a9490e51088b18eadf920d92e", "exif": {"FileSize": "2.1 MB", "FileType": "ZIP", "FileTypeExtension": "zip", "MIMEType": "application/zip", "ZipBitFlag": "0x0008", "ZipCRC": "0x051e89af", "ZipCompressedSize": 763, "ZipCompression": "Deflated", "ZipFileName": "META-INF/MANIFEST.MF", "ZipModifyDate": "2011:12:04 14:04:24", "ZipRequiredVersion": 20, "ZipUncompressedSize": 6875}, "ssdeep": "49152:2sROPUFizIpmpWZcXKtQ7+BmHMJGrAd6v0LsnmpgLa9UPgtK7QZWXc1S9S14j+B9:f", "sha224": "d31910c8a13def114eb9085bb7fdcbbb4961391bde0701012e661db8", "trid": {"0": "Android Package (73.9%)", "1": "Java Archive (20.4%)", "2": "ZIP compressed archive (5.6%)"}, "extension": "apk", "sha512": "9d49a63fc4533308d546a191c05297d4e8dbd8af3637ecd711e0a754833e18c851e1d2b417408d85c008bfdf6d9292d134e6e6148b9e6ad6bf5cf72353472e83", "filetype": "Zip archive data, at least v2.0 to extract", "size": 2228902, "sha1": "b1aab4bbff40eda2b31619da068b7aa5ec760bd2", "mimetype": "application/zip", "sha384": "b15d2fc8fd2961e69653535cf0ae52e18ba11d83cb97d389c8894040f3edfb5d04ae50ecd86d1c50bf9c588fe2b19685", "virustotal": {"permalink": "http://www.virustotal.com/file/1680fd004bfdda3fcf2792d8b7894dae605af008647693760fa3fdfa3677974c/analysis/", "scan_date": "2012-08-20 00:21:58", "positives": 26, "total": 41, "scans": {"TotalDefense": {"result": "AndroidOS/FakeInst.A!generic"}, "CAT-QuickHeal": {"result": "Android.BoxerSms.A"}, "AhnLab-V3": {"result": ""}, "Comodo": {"result": "UnclassifiedMalware"}, "TheHacker": {"result": ""}, "F-Prot": {"result": "ANDR/FakeInst.AE"}, "Fortinet": {"result": "Riskware/FakeInst!Android"}, "TrendMicro-HouseCall": {"result": "AndroidOS_BOXER.EMS"}, "SUPERAntiSpyware": {"result": ""}, "VBA32": {"result": "Trojan-SMS.AndroidOS.FakeInst.a"}, "BitDefender": {"result": "Android.Trojan.FakeInst.B"}, "TrendMicro": {"result": "AndroidOS_BOXER.EMS"}, "DrWeb": {"result": "Android.SmsSend.268"}, "ByteHero": {"result": ""}, "Symantec": {"result": "Android.Positmob"}, "Antiy-AVL": {"result": "Trojan/AndroidOS.FakeInst"}, "nProtect": {"result": ""}, "Norman": {"result": ""}, "McAfee": {"result": ""}, "Emsisoft": {"result": "Trojan.AndroidOS.FakeInst!IK"}, "ClamAV": {"result": ""}, "F-Secure": {"result": "Trojan:Android/Boxer.C"}, "Avast": {"result": "Android:FakeInst-N [Trj]"}, "Microsoft": {"result": "Program:AndroidOS/BoxerSms.A"}, "Commtouch": {"result": "ANDR/FakeInst.AE"}, "K7AntiVirus": {"result": "Riskware"}, "Kaspersky": {"result": "HEUR:Trojan-SMS.AndroidOS.FakeInst.a"}, "ViRobot": {"result": ""}, "GData": {"result": "Android.Trojan.FakeInst.B"}, "Ikarus": {"result": "Trojan.AndroidOS.FakeInst"}, "Sophos": {"result": "Andr/Boxer-A"}, "AntiVir": {"result": "Android/FakeInst.B.49"}, "AVG": {"result": ""}, "VIPRE": {"result": "Trojan.AndroidOS.Boxer.b (v)"}, "ESET-NOD32": {"result": "Android/TrojanSMS.Boxer.AQ.Gen"}, "Jiangmin": {"result": "Trojan/AndroidOS.ig"}, "VirusBuster": {"result": ""}, "McAfee-GW-Edition": {"result": ""}, "eSafe": {"result": ""}, "Rising": {"result": ""}, "Panda": {"result": ""}}}, "added_timestamp": "2012-11-02T14:22:24+00:00", "response": 1}