{"sha256": "1a48418de86b56447bb09e108eb1e8eeae261757c402ab0595245e0170c3288a", "extension": "apk", "ssdeep": "3072:HvRaI2xpj75nmVYosYUA+jn0QNRvG8OPabn0QNRvG8OPafn0QNRvG8OPaDuqRwjd:HvR9+Bh7ee0QNdGvPar0QNdGvPav0QNs", "sha384": "f2b09b03d0d2b662b35444f84f2996b243c88a1d00f0b05748c390b99d9280e68b27b6427b3dc8374b01324e777035f6", "sha1": "092c5e418438c340354034966ca32c997eef623e", "mimetype": "application/zip", "exif": {"FileSize": "148 kB", "FileType": "ZIP", "FileTypeExtension": "zip", "MIMEType": "application/zip", "ZipBitFlag": "0x0008", "ZipCRC": "0x11c22dee", "ZipCompressedSize": 526, "ZipCompression": "Deflated", "ZipFileName": "META-INF/MANIFEST.MF", "ZipModifyDate": "2012:03:01 20:07:15", "ZipRequiredVersion": 20, "ZipUncompressedSize": 1054}, "sha512": "8c3ee57282188653401bf81cb1e51b0ff0afce124c4cc15bc308268e208b1e4d5df597e6d89f157018e694dd4cb86f97b5d2bf98c427042f7f1bae9308ef6086", "filetype": "Zip archive data, at least v2.0 to extract", "md5": "5891ad0bc867f1af583fd7578443e89f", "size": 151134, "sha224": "bc95a84203bb142490a7825ac37c529dffad63495f8e3af123d72a6f", "trid": {"0": "Android Package (73.9%)", "1": "Java Archive (20.4%)", "2": "ZIP compressed archive (5.6%)"}, "virustotal": {"permalink": "http://www.virustotal.com/file/1a48418de86b56447bb09e108eb1e8eeae261757c402ab0595245e0170c3288a/analysis/", "scan_date": "2012-08-17 10:01:00", "positives": 19, "total": 37, "scans": {"TotalDefense": {"result": ""}, "CAT-QuickHeal": {"result": "Android.BoxerSms.C"}, "AhnLab-V3": {"result": ""}, "TheHacker": {"result": ""}, "F-Prot": {"result": ""}, "Fortinet": {"result": "Riskware/FakeInst!Android"}, "Microsoft": {"result": "Program:AndroidOS/BoxerSms.C"}, "SUPERAntiSpyware": {"result": ""}, "VBA32": {"result": "Trojan-SMS.AndroidOS.FakeInst.a"}, "TrendMicro": {"result": "AndroidOS_BOXER.DY"}, "DrWeb": {"result": "Android.SmsSend.668.origin"}, "ByteHero": {"result": ""}, "BitDefender": {"result": "Android.Trojan.FakeInst.AE"}, "Antiy-AVL": {"result": "Trojan/AndroidOS.FakeInst"}, "VIPRE": {"result": "Trojan.AndroidOS.Boxer.d (v)"}, "Norman": {"result": ""}, "McAfee": {"result": ""}, "ClamAV": {"result": ""}, "F-Secure": {"result": "Trojan:Android/Boxer.C"}, "Avast": {"result": "Android:FakeInst-AB [Trj]"}, "TrendMicro-HouseCall": {"result": "AndroidOS_BOXER.DY"}, "Commtouch": {"result": ""}, "K7AntiVirus": {"result": ""}, "Kaspersky": {"result": "HEUR:Trojan-SMS.AndroidOS.FakeInst.a"}, "GData": {"result": "Android.Trojan.FakeInst.AE"}, "Ikarus": {"result": "Trojan.AndroidOS.FakeInst"}, "Sophos": {"result": "Andr/Boxer-D"}, "AntiVir": {"result": "Android/FakeInst.AE.5"}, "AVG": {"result": ""}, "PCTools": {"result": ""}, "ESET-NOD32": {"result": "Android/TrojanSMS.Boxer.AQ.Gen"}, "Jiangmin": {"result": "Trojan/AndroidOS.anu"}, "VirusBuster": {"result": ""}, "McAfee-GW-Edition": {"result": ""}, "eSafe": {"result": ""}, "Rising": {"result": ""}, "Panda": {"result": ""}}}, "added_timestamp": "2012-11-02T18:26:57+00:00", "response": 1}