{"sha256": "c618412fc8c31a17262c41ba1366f633f1dc662db32d82ff4c0807c01b14a080", "virustotal": {"permalink": "http://www.virustotal.com/file/c618412fc8c31a17262c41ba1366f633f1dc662db32d82ff4c0807c01b14a080/analysis/", "scan_date": "2012-07-14 11:16:48", "positives": 16, "total": 42, "scans": {"TotalDefense": {"result": null}, "CAT-QuickHeal": {"result": "Android.FakeBrows.A"}, "AhnLab-V3": {"result": null}, "Comodo": {"result": "UnclassifiedMalware"}, "NOD32": {"result": "a variant of Android/TrojanSMS.FakeInst.S"}, "TheHacker": {"result": null}, "F-Prot": {"result": null}, "Fortinet": {"result": "Android/FakeInst.S!tr"}, "TrendMicro-HouseCall": {"result": "TROJ_GEN.FFFHZG3"}, "SUPERAntiSpyware": {"result": null}, "VIPRE": {"result": null}, "VBA32": {"result": null}, "BitDefender": {"result": "Android.Trojan.FakeInst.D"}, "TrendMicro": {"result": null}, "DrWeb": {"result": "Android.SmsSend.401"}, "ByteHero": {"result": null}, "Symantec": {"result": null}, "Antiy-AVL": {"result": "Trojan/AndroidOS.FakeInst"}, "nProtect": {"result": null}, "Norman": {"result": null}, "McAfee": {"result": null}, "Emsisoft": {"result": "AndroidOS.Trojan.FakeInst!IK"}, "ClamAV": {"result": null}, "F-Secure": {"result": "Trojan:Android/Fakeinst.K"}, "Avast": {"result": "Android:FakeBrows-A [Trj]"}, "ViRobot": {"result": null}, "Microsoft": {"result": null}, "K7AntiVirus": {"result": null}, "Kaspersky": {"result": "HEUR:Trojan-SMS.AndroidOS.FakeInst.a"}, "GData": {"result": "Android.Trojan.FakeInst.D"}, "Ikarus": {"result": "AndroidOS.Trojan.FakeInst"}, "Sophos": {"result": "Andr/Boxer-C"}, "AntiVir": {"result": null}, "Commtouch": {"result": null}, "AVG": {"result": null}, "PCTools": {"result": null}, "Jiangmin": {"result": "Backdoor/AndroidOS.cfw"}, "VirusBuster": {"result": null}, "McAfee-GW-Edition": {"result": null}, "eSafe": {"result": null}, "Rising": {"result": null}, "Panda": {"result": null}}}, "added_timestamp": "2012-12-18T10:33:13+00:00", "mimetype": "application/zip", "sha384": "823f491d9d3570289fede1b70fa71a704fde114f7cd3ac0bdd8b8e8e0333be50a965ac51e9573848a3f165f04154b0b6", "extension": "apk", "ssdeep": "1536:xJYkxllfwnHqh6KTNOqPH4Vm1ImOrLE4aiIphHMFVH0sTgnbKI:vlJ6dKTNOY4Y7ON1ILH2UsTgnOI", "size": 75019, "md5": "59c408c33235672505ebb5b29c9e0e6a", "filetype": "Zip archive data, at least v2.0 to extract", "sha224": "73250dd8d6e31455c2bcf6a3d02ac0ac4e94eb366a3c9890ceee8b44", "sha512": "1ecc87f43877284792cd0b833aa92914af255d7e7ac5a04cd2a9f7d577e59f4e8af8dd144a791d47cdc4287f9578670d1cb3cd3bba832bf45972d4ae991025e1", "exif": {"FileSize": "73 kB", "FileType": "ZIP", "FileTypeExtension": "zip", "MIMEType": "application/zip", "ZipBitFlag": "0x0008", "ZipCRC": "0x3a16aa33", "ZipCompressedSize": 810, "ZipCompression": "Deflated", "ZipFileName": "META-INF/MANIFEST.MF", "ZipModifyDate": "2012:07:11 13:47:11", "ZipRequiredVersion": 20, "ZipUncompressedSize": 2154}, "sha1": "53867664a3e75c7174b33d805cbc52cd80548aff", "trid": {"0": "Android Package (73.9%)", "1": "Java Archive (20.4%)", "2": "ZIP compressed archive (5.6%)"}, "response": 1}