{"sha256": "44c53bdd3a1d8a8b02dd815557a797b8034e423da5c4219079c63d04d0ed3f51", "virustotal": {"permalink": "http://www.virustotal.com/file/44c53bdd3a1d8a8b02dd815557a797b8034e423da5c4219079c63d04d0ed3f51/analysis/", "scan_date": "2012-05-26 04:23:12", "positives": 16, "total": 42, "scans": {"TotalDefense": {"result": null}, "CAT-QuickHeal": {"result": null}, "AhnLab-V3": {"result": null}, "Comodo": {"result": "UnclassifiedMalware"}, "NOD32": {"result": "Android/TrojanSMS.Boxer.BF"}, "TheHacker": {"result": null}, "F-Prot": {"result": null}, "Fortinet": {"result": "Android/Boxer.D"}, "TrendMicro-HouseCall": {"result": null}, "SUPERAntiSpyware": {"result": null}, "VIPRE": {"result": "Trojan.AndroidOS.Boxer.d (v)"}, "VBA32": {"result": null}, "BitDefender": {"result": "Android.Trojan.FakeInst.AS"}, "TrendMicro": {"result": null}, "DrWeb": {"result": "Android.SmsSend.395"}, "ByteHero": {"result": null}, "Symantec": {"result": null}, "Antiy-AVL": {"result": "Trojan/AndroidOS.FakeInst"}, "nProtect": {"result": null}, "Norman": {"result": null}, "McAfee": {"result": null}, "Emsisoft": {"result": "Trojan.Win32.SMSSend.AndroidOS.BoxerSms!IK"}, "ClamAV": {"result": null}, "F-Secure": {"result": "Trojan:Android/Boxer.C"}, "Avast": {"result": "Android:FakeInst-AB [Trj]"}, "Microsoft": {"result": "Program:AndroidOS/BoxerSms.D"}, "Commtouch": {"result": null}, "K7AntiVirus": {"result": null}, "Kaspersky": {"result": "HEUR:Trojan-SMS.AndroidOS.FakeInst.a"}, "ViRobot": {"result": null}, "GData": {"result": "Android.Trojan.FakeInst.AS"}, "Ikarus": {"result": "Trojan.Win32.SMSSend.AndroidOS.BoxerSms"}, "Sophos": {"result": "Andr/Boxer-D"}, "AntiVir": {"result": null}, "AVG": {"result": null}, "PCTools": {"result": null}, "Jiangmin": {"result": "Trojan/AndroidOS.bur"}, "VirusBuster": {"result": null}, "McAfee-GW-Edition": {"result": null}, "eSafe": {"result": null}, "Rising": {"result": null}, "Panda": {"result": null}}}, "added_timestamp": "2012-11-28T06:55:09+00:00", "sha384": "708fc9241e6f0ba9cd402a275fd807d6e6a617f28773af77b1edd0f4e8835e53a8ae8084631329ad51b4ff1be1215d02", "mimetype": "application/zip", "ssdeep": "3072:DL/cZPBswU1n5auQMXC36JkswU1n5auQMXC36J4swU1n5auQMXC36J5swU1n5auD:sPCwU6yXayLwU6yXayvwU6yXay6wU6yd", "sha224": "7f897cfcee6446c9837ecd9babd8e21eaf58045edbf7146d65cdd429", "exif": {"FileSize": "145 kB", "FileType": "ZIP", "FileTypeExtension": "zip", "MIMEType": "application/zip", "ZipBitFlag": "0x0808", "ZipCRC": "0x51a99d99", "ZipCompressedSize": 659, "ZipCompression": "Deflated", "ZipFileName": "META-INF/MANIFEST.MF", "ZipModifyDate": "2012:05:23 02:38:13", "ZipRequiredVersion": 20, "ZipUncompressedSize": 1461}, "trid": {"0": "Android Package (73.9%)", "1": "Java Archive (20.4%)", "2": "ZIP compressed archive (5.6%)"}, "filetype": "Zip archive data, at least v2.0 to extract", "extension": "apk", "size": 148801, "sha512": "cbaca5880b9a55d30d568c0945acec5f496869043084fd20311badf0a121664031294b963ce2ed894fbac2267a35ef0b993dc4cdc327577002e46f157ab2ece8", "sha1": "2d4ecd7695d2717c07598ca69f5b3a53aae2626d", "md5": "59ff41e883029d1234c981149234131e", "response": 1}