{"sha256": "6582445e1505fd2be58221463fafd63b10bfd70dbd778a49e4dbc3d76026895a", "virustotal": {"permalink": "http://www.virustotal.com/file/6582445e1505fd2be58221463fafd63b10bfd70dbd778a49e4dbc3d76026895a/analysis/", "scan_date": "2012-06-18 17:28:38", "positives": 16, "total": 42, "scans": {"TotalDefense": {"result": null}, "CAT-QuickHeal": {"result": null}, "AhnLab-V3": {"result": null}, "Comodo": {"result": "UnclassifiedMalware"}, "NOD32": {"result": "Android/TrojanSMS.Boxer.AQ.Gen"}, "TheHacker": {"result": null}, "F-Prot": {"result": null}, "Fortinet": {"result": "Riskware/FakeInst!Android"}, "TrendMicro-HouseCall": {"result": null}, "SUPERAntiSpyware": {"result": null}, "VIPRE": {"result": "Trojan.AndroidOS.Boxer.d (v)"}, "VBA32": {"result": null}, "BitDefender": {"result": "Android.Trojan.FakeInst.AS"}, "TrendMicro": {"result": null}, "DrWeb": {"result": "Android.SmsSend.395"}, "ByteHero": {"result": null}, "Symantec": {"result": null}, "Antiy-AVL": {"result": "Trojan/AndroidOS.FakeInst"}, "nProtect": {"result": null}, "Norman": {"result": null}, "McAfee": {"result": null}, "Emsisoft": {"result": "Trojan.Win32.SMSSend.AndroidOS.BoxerSms!IK"}, "ClamAV": {"result": null}, "F-Secure": {"result": "Trojan:Android/Boxer.C"}, "Avast": {"result": "Android:FakeInst-AB [Trj]"}, "Microsoft": {"result": "Program:AndroidOS/BoxerSms.D"}, "Commtouch": {"result": null}, "K7AntiVirus": {"result": null}, "Kaspersky": {"result": "HEUR:Trojan-SMS.AndroidOS.FakeInst.a"}, "ViRobot": {"result": null}, "GData": {"result": "Android.Trojan.FakeInst.AS"}, "Ikarus": {"result": "Trojan.Win32.SMSSend.AndroidOS.BoxerSms"}, "Sophos": {"result": "Andr/Boxer-D"}, "AntiVir": {"result": null}, "AVG": {"result": null}, "PCTools": {"result": null}, "Jiangmin": {"result": "Trojan/AndroidOS.bzf"}, "VirusBuster": {"result": null}, "McAfee-GW-Edition": {"result": null}, "eSafe": {"result": null}, "Rising": {"result": null}, "Panda": {"result": null}}}, "added_timestamp": "2012-11-14T23:29:43+00:00", "md5": "70965c620116201ddde8c4a207058dfc", "filetype": "Zip archive data, at least v2.0 to extract", "trid": {"0": "Android Package (73.9%)", "1": "Java Archive (20.4%)", "2": "ZIP compressed archive (5.6%)"}, "sha512": "f26ecc749eb68022240080d616d58d8b9a9633316bb747e29ad8b9941aabf6cd1d89ac9f09040fde31b98a5ffc011d84c7d441f7573118da560b5acf60a9106f", "sha384": "41bbd6ab76d9d05fefdc9b91e9acdd26de363d2a80821734d1c950149188f258f999cdc6623fb939de802536e0f5368f", "extension": "apk", "sha1": "9f5a8ff26b3ea8ba48e60b704bdf0216a9e17a50", "ssdeep": "6144:xTvR9+BnvR9+BSvR9+BVvR9+BAvR9+BZK9PKwU6yXayTwU6yXay3wU6yXayiwU6I:HkJk0kLk2kZK97U63U6bU6QU6w4F93A", "mimetype": "application/zip", "sha224": "91f8b2fdb9fb53a7b6d0c3010e7ffa793aa1fae0d04e09c418e7c9ff", "exif": {"FileSize": "256 kB", "FileType": "ZIP", "FileTypeExtension": "zip", "MIMEType": "application/zip", "ZipBitFlag": "0x0808", "ZipCRC": "0x9e391b87", "ZipCompressedSize": 921, "ZipCompression": "Deflated", "ZipFileName": "META-INF/MANIFEST.MF", "ZipModifyDate": "2012:06:15 19:36:05", "ZipRequiredVersion": 20, "ZipUncompressedSize": 2481}, "size": 262566, "response": 1}