{"sha256": "39e79a9350d3377a825671c79df23a33bb1a0961b3175407fd87f47c2b938a5e", "extension": "apk", "trid": {"0": "Android Package (73.9%)", "1": "Java Archive (20.4%)", "2": "ZIP compressed archive (5.6%)"}, "size": 422004, "ssdeep": "6144:l2u7gntexDkP8+s4rY7eMzQcPSu4QJyOZGxu37FDZkh9TWnQitVgRj3:l2uYIxDY8+FdjcmQkOZ++pZk/6QyVQz", "filetype": "Zip archive data, at least v2.0 to extract", "mimetype": "application/zip", "md5": "74b88f463afbe1b7bd1d1c2ec706565b", "sha224": "878a9f4de6365a53623baca97a4c5d2a8d25ddd19ddc441f562c8154", "exif": {"FileSize": "412 kB", "FileType": "ZIP", "FileTypeExtension": "zip", "MIMEType": "application/zip", "ZipBitFlag": "0x0008", "ZipCRC": "0x0420b3ae", "ZipCompressedSize": 4917, "ZipCompression": "Deflated", "ZipFileName": "META-INF/MANIFEST.MF", "ZipModifyDate": "2012:06:06 16:29:23", "ZipRequiredVersion": 20, "ZipUncompressedSize": 12980}, "sha512": "5009a9778fbe44974b37028e04cfb8072c8b8fca83bf1d9cc058111964c33e22a950dca8ce9832d799816c01763755d0b04ad115d3ad504aec9da46af96f5440", "sha1": "8d75f0a0941cc6196c44493b207fc458f54284c5", "sha384": "fbdd85428279e912158df14fd3735bd8b4ec0b53e8685716b5cd0ed9c304cee54b719e5a5d600143e54131b7e593f32e", "virustotal": {"permalink": "http://www.virustotal.com/file/39e79a9350d3377a825671c79df23a33bb1a0961b3175407fd87f47c2b938a5e/analysis/", "scan_date": "2012-11-01 14:49:08", "positives": 13, "total": 44, "scans": {"TotalDefense": {"result": ""}, "CAT-QuickHeal": {"result": "Android.Smshider.C85c"}, "AhnLab-V3": {"result": ""}, "MicroWorld-eScan": {"result": "Android/JSmsHider.B (ES)"}, "F-Prot": {"result": ""}, "Fortinet": {"result": "Android/JSmsH.A"}, "ViRobot": {"result": ""}, "SUPERAntiSpyware": {"result": ""}, "ESET-NOD32": {"result": "Android/JSmsHider.B"}, "BitDefender": {"result": ""}, "Antiy-AVL": {"result": ""}, "AntiVir": {"result": ""}, "Emsisoft": {"result": ""}, "eSafe": {"result": ""}, "Sophos": {"result": "Andr/JSmsH-A"}, "McAfee": {"result": ""}, "AVG": {"result": "Android_dc.EEL"}, "nProtect": {"result": ""}, "Jiangmin": {"result": ""}, "PCTools": {"result": ""}, "Comodo": {"result": "UnclassifiedMalware"}, "McAfee-GW-Edition": {"result": ""}, "Agnitum": {"result": ""}, "TrendMicro": {"result": "AndroidOS_SMSHIDER.BLK"}, "DrWeb": {"result": ""}, "ByteHero": {"result": ""}, "Symantec": {"result": ""}, "VIPRE": {"result": ""}, "Norman": {"result": ""}, "ClamAV": {"result": ""}, "F-Secure": {"result": "Trojan:Android/DiHes.B"}, "Avast": {"result": "Android:JSmsHider-BC [Trj]"}, "Kingsoft": {"result": ""}, "TrendMicro-HouseCall": {"result": "AndroidOS_SMSHIDER.BLK"}, "Commtouch": {"result": ""}, "K7AntiVirus": {"result": ""}, "Kaspersky": {"result": ""}, "GData": {"result": "Android:JSmsHider-BC "}, "Ikarus": {"result": "AndroidOS.JSmsHider.C"}, "Microsoft": {"result": ""}, "VBA32": {"result": ""}, "TheHacker": {"result": ""}, "Rising": {"result": ""}, "Panda": {"result": ""}}}, "added_timestamp": "2012-11-09T20:52:43+00:00", "response": 1}