{"sha256": "acf68698d82acd136e9ec18a5c8bfa0760d6f6637eb61125362dc42004e73eb8", "virustotal": {"permalink": "http://www.virustotal.com/file/acf68698d82acd136e9ec18a5c8bfa0760d6f6637eb61125362dc42004e73eb8/analysis/", "scan_date": "2011-12-31 04:43:16", "positives": 5, "total": 43, "scans": {"CAT-QuickHeal": {"result": ""}, "AhnLab-V3": {"result": ""}, "Comodo": {"result": "UnclassifiedMalware"}, "NOD32": {"result": "Android/TrojanSMS.FakeInst.K"}, "TheHacker": {"result": ""}, "F-Prot": {"result": ""}, "Fortinet": {"result": ""}, "TrendMicro-HouseCall": {"result": ""}, "SUPERAntiSpyware": {"result": ""}, "Prevx": {"result": ""}, "VIPRE": {"result": ""}, "VBA32": {"result": ""}, "BitDefender": {"result": ""}, "TrendMicro": {"result": ""}, "DrWeb": {"result": ""}, "ByteHero": {"result": ""}, "Sophos": {"result": ""}, "Symantec": {"result": ""}, "Antiy-AVL": {"result": ""}, "nProtect": {"result": ""}, "Norman": {"result": ""}, "McAfee": {"result": ""}, "Emsisoft": {"result": ""}, "ClamAV": {"result": ""}, "F-Secure": {"result": ""}, "Avast": {"result": "Android:FakeInst-Q [Trj]"}, "Microsoft": {"result": "Trojan:AndroidOS/FakeInstSms.A"}, "Commtouch": {"result": ""}, "K7AntiVirus": {"result": ""}, "Kaspersky": {"result": ""}, "ViRobot": {"result": ""}, "GData": {"result": "Android:FakeInst-Q "}, "Ikarus": {"result": ""}, "eTrust-Vet": {"result": ""}, "AntiVir": {"result": ""}, "AVG": {"result": ""}, "PCTools": {"result": ""}, "Jiangmin": {"result": ""}, "VirusBuster": {"result": ""}, "McAfee-GW-Edition": {"result": ""}, "eSafe": {"result": ""}, "Rising": {"result": ""}, "Panda": {"result": ""}}}, "added_timestamp": "2012-11-22T15:04:27+00:00", "md5": "7ebb95e996767d8a591e932161030c41", "sha384": "8053c3f86257577555569d80527554867034b775a8e8c96fe88ef1d721715bb9148d09d394a47a87c4c294f783b0b66b", "filetype": "Zip archive data, at least v2.0 to extract", "sha224": "6675243cd8ee58d0951bf3c132fde2fd1a088618762b869955482000", "sha512": "1e296e84d3d3d554ae24cd1379de9441ecb48501508988fbbce8c950fa47a242c34308a068a70bf0942212b41e35e053bdcfb5fe7fe2efe04dae0c493a631e23", "mimetype": "application/zip", "sha1": "540f7512622460494f92d7c18e7a43ff16bfc5a1", "ssdeep": "768:uFBWgbxRdA+P2kKA+P/mH6A+Pu2AAo0ZVs1dr0K1KGYOmE4/UG6zqFCzqFzzqFys:u7rDek83oM9AAouFK4GTmR/x6G0G1GA+", "size": 62646, "exif": {"FileSize": "61 kB", "FileType": "ZIP", "FileTypeExtension": "zip", "MIMEType": "application/zip", "ZipBitFlag": "0x0008", "ZipCRC": "0xaaa1d948", "ZipCompressedSize": 658, "ZipCompression": "Deflated", "ZipFileName": "META-INF/MANIFEST.MF", "ZipModifyDate": "2011:12:28 03:20:28", "ZipRequiredVersion": 20, "ZipUncompressedSize": 1763}, "trid": {"0": "Android Package (73.9%)", "1": "Java Archive (20.4%)", "2": "ZIP compressed archive (5.6%)"}, "extension": "apk", "response": 1}