{"sha256": "9dbea897ce6942459a7f88749763434ea1e06aa0d76a8b1dbfc22231197bb55f", "virustotal": {"permalink": "http://www.virustotal.com/file/9dbea897ce6942459a7f88749763434ea1e06aa0d76a8b1dbfc22231197bb55f/analysis/", "scan_date": "2012-06-18 15:10:15", "positives": 16, "total": 41, "scans": {"TotalDefense": {"result": null}, "CAT-QuickHeal": {"result": null}, "Comodo": {"result": "UnclassifiedMalware"}, "NOD32": {"result": "Android/TrojanSMS.Boxer.AQ.Gen"}, "TheHacker": {"result": null}, "F-Prot": {"result": null}, "Fortinet": {"result": "Riskware/FakeInst!Android"}, "Microsoft": {"result": "Program:AndroidOS/BoxerSms.D"}, "SUPERAntiSpyware": {"result": null}, "VIPRE": {"result": "Trojan.AndroidOS.Boxer.d (v)"}, "VBA32": {"result": null}, "BitDefender": {"result": "Android.Trojan.FakeInst.AS"}, "TrendMicro": {"result": null}, "DrWeb": {"result": "Android.SmsSend.395"}, "ByteHero": {"result": null}, "Symantec": {"result": null}, "Antiy-AVL": {"result": "Trojan/AndroidOS.FakeInst"}, "nProtect": {"result": null}, "Norman": {"result": null}, "McAfee": {"result": null}, "Emsisoft": {"result": "Trojan.Win32.SMSSend.AndroidOS.BoxerSms!IK"}, "ClamAV": {"result": null}, "F-Secure": {"result": "Trojan:Android/Boxer.C"}, "Avast": {"result": "Android:FakeInst-AB [Trj]"}, "TrendMicro-HouseCall": {"result": null}, "Commtouch": {"result": null}, "K7AntiVirus": {"result": null}, "Kaspersky": {"result": "HEUR:Trojan-SMS.AndroidOS.FakeInst.a"}, "ViRobot": {"result": null}, "GData": {"result": "Android.Trojan.FakeInst.AS"}, "Ikarus": {"result": "Trojan.Win32.SMSSend.AndroidOS.BoxerSms"}, "Sophos": {"result": "Andr/Boxer-D"}, "AntiVir": {"result": null}, "AVG": {"result": null}, "PCTools": {"result": null}, "Jiangmin": {"result": "Trojan/AndroidOS.bzf"}, "VirusBuster": {"result": null}, "McAfee-GW-Edition": {"result": null}, "eSafe": {"result": null}, "Rising": {"result": null}, "Panda": {"result": null}}}, "added_timestamp": "2012-11-26T00:28:48+00:00", "ssdeep": "12288:zkrkKkpkUkrkWkKkpkAkHkWk1k8kTk5M7lU6JU6NU66U6qWkEXFq:YQVKrQpVKfEpeT45MRJN6q/cFq", "sha384": "ecfae370ed0867db9eeabc5cebbc11554cd9654e0b7f2e91717f939f7c92d561a522429890271e3ad6e80594976f9b64", "md5": "8a5c23178df5ebe62170a70ebb4413de", "extension": "apk", "trid": {"0": "Android Package (73.9%)", "1": "Java Archive (20.4%)", "2": "ZIP compressed archive (5.6%)"}, "size": 477613, "sha224": "91761ab4447f5e973adf8caac8063fa5007d3fdd18f8fa6b9a72acc9", "exif": {"FileSize": "466 kB", "FileType": "ZIP", "FileTypeExtension": "zip", "MIMEType": "application/zip", "ZipBitFlag": "0x0808", "ZipCRC": "0xd71acad0", "ZipCompressedSize": 966, "ZipCompression": "Deflated", "ZipFileName": "META-INF/MANIFEST.MF", "ZipModifyDate": "2012:06:15 18:03:10", "ZipRequiredVersion": 20, "ZipUncompressedSize": 3206}, "sha512": "23c0e3ba19b8a58f36ecd5cf7a2c689aa8e9eb372c8f897431dc6285fc75ed2114d8b7eb68ac473e0b55b07d981752158377b24a4a6109846a6c7d5eb94d9a82", "mimetype": "application/zip", "filetype": "Zip archive data, at least v2.0 to extract", "sha1": "d10f0f14f5912d8bd3f5e7d20231bae61c52da92", "response": 1}