{"sha256": "f9a9d688786c72852fe2e8a88f81cf88920f316f86bc4d985a90c0380d3a4acc", "virustotal": {"permalink": "http://www.virustotal.com/file/f9a9d688786c72852fe2e8a88f81cf88920f316f86bc4d985a90c0380d3a4acc/analysis/", "scan_date": "2012-08-20 03:40:54", "positives": 26, "total": 42, "scans": {"TotalDefense": {"result": null}, "CAT-QuickHeal": {"result": "Android.BoxerSms.B"}, "AhnLab-V3": {"result": null}, "Comodo": {"result": "UnclassifiedMalware"}, "TheHacker": {"result": null}, "F-Prot": {"result": "ANDR/FakeInst.F"}, "Fortinet": {"result": "Riskware/FakeInst!Android"}, "TrendMicro-HouseCall": {"result": "AndroidOS_BOXER.DY"}, "SUPERAntiSpyware": {"result": null}, "VIPRE": {"result": "Trojan.AndroidOS.FakeInst.d (v)"}, "VBA32": {"result": "Trojan-SMS.AndroidOS.FakeInst.a"}, "BitDefender": {"result": "Android.Trojan.FakeInst.D"}, "TrendMicro": {"result": "AndroidOS_BOXER.DY"}, "DrWeb": {"result": "Android.SmsSend.401"}, "ByteHero": {"result": null}, "Symantec": {"result": "Android.Fakemini"}, "Antiy-AVL": {"result": "Trojan/win32.agent"}, "nProtect": {"result": null}, "Norman": {"result": null}, "McAfee": {"result": null}, "Emsisoft": {"result": "Trojan.AndroidOS.FakeInst!IK"}, "ClamAV": {"result": null}, "F-Secure": {"result": "Trojan:Android/Fakeinst.E"}, "Avast": {"result": "Android:FakeBrows-A [Trj]"}, "Microsoft": {"result": "Program:AndroidOS/BoxerSms.B"}, "Commtouch": {"result": "ANDR/FakeInst.F"}, "K7AntiVirus": {"result": "Riskware"}, "Kaspersky": {"result": "HEUR:Trojan-SMS.AndroidOS.FakeInst.a"}, "ViRobot": {"result": null}, "GData": {"result": "Android:FakeBrows-A "}, "Ikarus": {"result": "Trojan.AndroidOS.FakeInst"}, "Sophos": {"result": "Andr/Boxer-C"}, "AntiVir": {"result": "Android/FakeInst.A"}, "AVG": {"result": null}, "PCTools": {"result": "Android.Fakemini"}, "ESET-NOD32": {"result": "Android/TrojanSMS.FakeInst.D"}, "Jiangmin": {"result": "Trojan/AndroidOS.cos"}, "VirusBuster": {"result": null}, "McAfee-GW-Edition": {"result": null}, "eSafe": {"result": null}, "Rising": {"result": null}, "Panda": {"result": null}}}, "added_timestamp": "2012-12-18T00:14:38+00:00", "trid": {"0": "Android Package (73.9%)", "1": "Java Archive (20.4%)", "2": "ZIP compressed archive (5.6%)"}, "exif": {"FileSize": "282 kB", "FileType": "ZIP", "FileTypeExtension": "zip", "MIMEType": "application/zip", "ZipBitFlag": "0x0008", "ZipCRC": "0x397d840e", "ZipCompressedSize": 851, "ZipCompression": "Deflated", "ZipFileName": "META-INF/MANIFEST.MF", "ZipModifyDate": "2012:02:25 12:11:06", "ZipRequiredVersion": 20, "ZipUncompressedSize": 2222}, "sha224": "84d26c6a8377f06564f9f9d07d43004e0f715877ca62ba91aea8df80", "sha1": "85b3a84fd677197ca0a3c40c66a88eae38ff100f", "size": 288876, "ssdeep": "6144:/xKZZ3EZImXGsPEHqIRLZj3lCEVsrTlmBqT1a9a:WiMrRR3lCEV8F1d", "md5": "93246459ed3be462f87be8b141b1f387", "filetype": "Zip archive data, at least v2.0 to extract", "sha512": "673e79499596b3756fd5cc130a1ae8cc61dc57c7ca11482961b9ce2c4ccbda41b952cf683ba27cd3d753810c5c8b74c71d53d7ee2c6aecadd896f58e8bf28289", "mimetype": "application/zip", "extension": "apk", "sha384": "900f58b8493337d7a69169612ba13e0bb51bf8c09bd390464b95415fc96dc81619ea7fadf207c6ba306d5c80ec83dc58", "response": 1}