{"sha256": "f85f6daae96817d1d28f0a72645336a8327ab04ad3ba8ea1e7aa1b1b21c3bb53", "virustotal": {"permalink": "http://www.virustotal.com/file/f85f6daae96817d1d28f0a72645336a8327ab04ad3ba8ea1e7aa1b1b21c3bb53/analysis/", "scan_date": "2012-06-18 15:04:23", "positives": 16, "total": 39, "scans": {"TotalDefense": {"result": null}, "CAT-QuickHeal": {"result": null}, "Comodo": {"result": "UnclassifiedMalware"}, "TrendMicro-HouseCall": {"result": null}, "NOD32": {"result": "Android/TrojanSMS.Boxer.AQ.Gen"}, "TheHacker": {"result": null}, "F-Prot": {"result": null}, "Fortinet": {"result": "Riskware/FakeInst!Android"}, "Microsoft": {"result": "Program:AndroidOS/BoxerSms.D"}, "SUPERAntiSpyware": {"result": null}, "VIPRE": {"result": "Trojan.AndroidOS.Boxer.d (v)"}, "BitDefender": {"result": "Android.Trojan.FakeInst.AS"}, "TrendMicro": {"result": null}, "DrWeb": {"result": "Android.SmsSend.395"}, "ByteHero": {"result": null}, "Symantec": {"result": null}, "Antiy-AVL": {"result": "Trojan/AndroidOS.FakeInst"}, "nProtect": {"result": null}, "McAfee": {"result": null}, "Emsisoft": {"result": "Trojan.Win32.SMSSend.AndroidOS.BoxerSms!IK"}, "ClamAV": {"result": null}, "F-Secure": {"result": "Trojan:Android/Boxer.C"}, "Avast": {"result": "Android:FakeInst-AB [Trj]"}, "ViRobot": {"result": null}, "Commtouch": {"result": null}, "K7AntiVirus": {"result": null}, "Kaspersky": {"result": "HEUR:Trojan-SMS.AndroidOS.FakeInst.a"}, "GData": {"result": "Android.Trojan.FakeInst.AS"}, "Ikarus": {"result": "Trojan.Win32.SMSSend.AndroidOS.BoxerSms"}, "Sophos": {"result": "Andr/Boxer-D"}, "AntiVir": {"result": null}, "AVG": {"result": null}, "PCTools": {"result": null}, "Jiangmin": {"result": "Trojan/AndroidOS.bzf"}, "VirusBuster": {"result": null}, "McAfee-GW-Edition": {"result": null}, "eSafe": {"result": null}, "Rising": {"result": null}, "Panda": {"result": null}}}, "added_timestamp": "2012-12-10T04:28:32+00:00", "sha384": "2a4116a72098c62320a109d9ea0d0cd859b9d13cf978ab3eb1fafec77a63119930d8f803d2fbae5e85d8c492c4348171", "sha512": "0e64619b72b2c31081cae5d09e941b4ae9551743eaaca1fdb2385ad1f95541ace8f5b0de4034d14eb8c9e17b88919ee6185d7a081cbdeefbbafdf826904819a6", "ssdeep": "12288:ak8k3kwklkGkbkxkSkPkok9kekrkUkjDIcU6KU6mU6ZU6bRGccCA:lT0POZAS9sHGxQrjDdKmZbVcCA", "exif": {"FileSize": "466 kB", "FileType": "ZIP", "FileTypeExtension": "zip", "MIMEType": "application/zip", "ZipBitFlag": "0x0808", "ZipCRC": "0x59193f8f", "ZipCompressedSize": 963, "ZipCompression": "Deflated", "ZipFileName": "META-INF/MANIFEST.MF", "ZipModifyDate": "2012:06:15 18:18:26", "ZipRequiredVersion": 20, "ZipUncompressedSize": 3206}, "md5": "b37bb4db3e4ea0c11b2f92904ef062c1", "mimetype": "application/zip", "filetype": "Zip archive data, at least v2.0 to extract", "extension": "apk", "trid": {"0": "Android Package (73.9%)", "1": "Java Archive (20.4%)", "2": "ZIP compressed archive (5.6%)"}, "size": 477659, "sha1": "c1ac663ea1d8c475974831d15d02aa51bde068aa", "sha224": "29bf78fb8b5496ae6933e74e7decdd10af70666d791f8277a7fb5d85", "response": 1}