{"sha256": "ba1aa326ca5b79e79feba9bbfe85f238b63c317d9329f1f7c28d54fe905353b9", "virustotal": {"permalink": "http://www.virustotal.com/file/ba1aa326ca5b79e79feba9bbfe85f238b63c317d9329f1f7c28d54fe905353b9/analysis/", "scan_date": "2012-06-22 19:01:29", "positives": 32, "total": 42, "scans": {"TotalDefense": {"result": ""}, "CAT-QuickHeal": {"result": "Android.Spitmo.A"}, "AhnLab-V3": {"result": ""}, "Comodo": {"result": "TrojWare.Win32.Agent.~AOT"}, "NOD32": {"result": "Android/Spy.Spitmo.A"}, "TheHacker": {"result": ""}, "F-Prot": {"result": "ANDR/Spitmo.A"}, "Fortinet": {"result": "Android/Spitmo.B!tr.spy"}, "TrendMicro-HouseCall": {"result": "AndroidOS_Spitmo.A"}, "SUPERAntiSpyware": {"result": ""}, "VIPRE": {"result": "Trojan.AndroidOS.Spitmo.a (v)"}, "VBA32": {"result": "Trojan-Spy.AndroidOS.Spitmo.a"}, "BitDefender": {"result": "Android.Trojan.Spitmo.A"}, "TrendMicro": {"result": "AndroidOS_Spitmo.A"}, "DrWeb": {"result": "Android.SpyEye.1"}, "ByteHero": {"result": ""}, "Symantec": {"result": "Android.Premiumtext"}, "Antiy-AVL": {"result": "Trojan/AndroidOS.Spitmo"}, "nProtect": {"result": ""}, "Norman": {"result": "Suspicious_Gen2.RBJBG"}, "McAfee": {"result": "Android/Spitmo"}, "Emsisoft": {"result": "Trojan-Spy.AndroidOS.Spitmo!IK"}, "ClamAV": {"result": "Mobile.Simseg-1"}, "F-Secure": {"result": "Trojan:Android/Spitmo.A"}, "Avast": {"result": "Android:Spitmo-A [Trj]"}, "Microsoft": {"result": "Trojan:AndroidOS/Spitmo.A"}, "Commtouch": {"result": "ANDR/Spitmo.A"}, "K7AntiVirus": {"result": "Riskware"}, "Kaspersky": {"result": "Trojan-Spy.AndroidOS.Spitmo.a"}, "ViRobot": {"result": ""}, "GData": {"result": "Android.Trojan.Spitmo.A"}, "Ikarus": {"result": "Trojan-Spy.AndroidOS.Spitmo"}, "Sophos": {"result": "Andr/Spitmo-A"}, "AntiVir": {"result": "TR/Android.Spitmo.A"}, "AVG": {"result": ""}, "PCTools": {"result": "Android.Spitmo"}, "Jiangmin": {"result": "TrojanSpy.AndroidOS.dz"}, "VirusBuster": {"result": "TrojanSpy.AndroidOS.Spitmo.A"}, "McAfee-GW-Edition": {"result": "Android/Spitmo"}, "eSafe": {"result": ""}, "Rising": {"result": ""}, "Panda": {"result": "Android/Spitmo.A"}}}, "added_timestamp": "2012-07-26T18:07:10+00:00", "trid": {"0": "Android Package (92.9%)", "1": "ZIP compressed archive (7.0%)"}, "sha512": "c03d3f85ce34be085979b10d62a5cc27d49ea64e18ddab22e07efa9c27b97b97b83cc2fef67b4a23d49be1e57bbf7e4cdf256e99d5907a805eb32fdf4e158bc1", "sha224": "a34458e1d93834e4587df9aebc311bffeea94f45887b7753f8f04720", "mimetype": "application/java-archive", "ssdeep": "384:yexl+Jldosp2JjUe/1QXMq9L1hK/TWJ+Y1bgzdfDw5CmNOU+Do1PYair:jxlWldosp2JjUYw19LSFgoSNBty", "exif": {"FileSize": "19 kB", "FileType": "ZIP", "FileTypeExtension": "zip", "MIMEType": "application/zip", "ZipBitFlag": "0x0008", "ZipCRC": "0xc44ab3f0", "ZipCompressedSize": 335, "ZipCompression": "Deflated", "ZipFileName": "META-INF/MANIFEST.MF", "ZipModifyDate": "2011:07:22 17:00:23", "ZipRequiredVersion": 20, "ZipUncompressedSize": 572}, "md5": "cfa9edb8c9648ae2757a85e6066f6515", "sha1": "604b0d72b9e995a7d95ef42561acb1ede4949fdb", "extension": "apk", "size": 19724, "filetype": "Java archive data (JAR)", "sha384": "4689f6ec51fd608ebfa7c7309126f29c70ac9705ef9b2252c9e24c2890f22ee59ad289c1fe78a76d120a6a35774109b3", "response": 1}