{"sha256": "12376111410625054efee0491c30d9fa3aa029e5b716025592a2f5471a3f1533", "sha1": "2d2b456302d9ef06a022ec4bd16a0c83ac1b174f", "filetype": "Zip archive data, at least v2.0 to extract", "trid": {"0": "Android Package (73.9%)", "1": "Java Archive (20.4%)", "2": "ZIP compressed archive (5.6%)"}, "size": 477606, "ssdeep": "12288:Tkxk4kfkukNkMk8kTkek9kokPkKkpkBiVTU6rU6HU6MU6IsO2iVi:4SX8BWjT4xGHsVKBiNrHMIZzVi", "mimetype": "application/zip", "exif": {"FileSize": "466 kB", "FileType": "ZIP", "FileTypeExtension": "zip", "MIMEType": "application/zip", "ZipBitFlag": "0x0808", "ZipCRC": "0x9673d28f", "ZipCompressedSize": 963, "ZipCompression": "Deflated", "ZipFileName": "META-INF/MANIFEST.MF", "ZipModifyDate": "2012:06:15 19:08:26", "ZipRequiredVersion": 20, "ZipUncompressedSize": 3206}, "sha384": "e7283cf3565dbe3f7b4f59e858d59c3b735f24e2fb48e5263f6ae79beb94272becb64ad397b86773062ce823c0fb4591", "extension": "apk", "sha512": "dc0c2d10cb9e6bb05e7cbf15620853db1fa07bb6b41c8abc1f3bf1796a82887487610cb87bf190d2ddc8acd0b013af60240e7a462db201bcd693902ddb4db910", "md5": "e57ced3fdfa7b8f478decbbdda8322a6", "sha224": "dceb379a9bf337728a87e0efb63184aa4da21ef056db3ddf0b459872", "virustotal": {"permalink": "http://www.virustotal.com/file/12376111410625054efee0491c30d9fa3aa029e5b716025592a2f5471a3f1533/analysis/", "scan_date": "2012-08-21 07:54:22", "positives": 16, "total": 30, "scans": {"TotalDefense": {"result": ""}, "CAT-QuickHeal": {"result": "Android.BoxerSms.D"}, "AhnLab-V3": {"result": ""}, "TheHacker": {"result": ""}, "F-Prot": {"result": "ANDR/FakeInst.T"}, "Fortinet": {"result": "Riskware/FakeInst!Android"}, "TrendMicro-HouseCall": {"result": "TROJ_GEN.RFFH1FL"}, "SUPERAntiSpyware": {"result": ""}, "ByteHero": {"result": ""}, "TrendMicro": {"result": "AndroidOS_TROJFAKEInst.A"}, "DrWeb": {"result": "Android.SmsSend.395"}, "ESET-NOD32": {"result": "Android/TrojanSMS.Boxer.AQ.Gen"}, "Antiy-AVL": {"result": "Trojan/AndroidOS.FakeInst"}, "VIPRE": {"result": "Trojan.AndroidOS.Boxer.d (v)"}, "Norman": {"result": ""}, "McAfee": {"result": ""}, "ClamAV": {"result": ""}, "F-Secure": {"result": "Trojan:Android/Boxer.C"}, "Commtouch": {"result": "ANDR/FakeInst.T"}, "K7AntiVirus": {"result": "Riskware"}, "eSafe": {"result": ""}, "Ikarus": {"result": "Trojan.AndroidOS.BoxerSms"}, "Sophos": {"result": "Andr/Boxer-D"}, "AntiVir": {"result": "Android/BoxerSms.D"}, "AVG": {"result": ""}, "Jiangmin": {"result": "Trojan/AndroidOS.bzf"}, "Panda": {"result": ""}, "McAfee-GW-Edition": {"result": ""}, "Rising": {"result": ""}, "VBA32": {"result": ""}}}, "added_timestamp": "2012-11-05T20:30:01+00:00", "response": 1}