{"sha256": "3082b95ea6f4d30002aef371f3edae74ed87575b0b122a2f9fad9cf3dba3b311", "virustotal": {"permalink": "http://www.virustotal.com/file/3082b95ea6f4d30002aef371f3edae74ed87575b0b122a2f9fad9cf3dba3b311/analysis/", "scan_date": "2012-08-22 18:29:10", "positives": 22, "total": 42, "scans": {"TotalDefense": {"result": null}, "CAT-QuickHeal": {"result": "Android.BoxerSms.D"}, "AhnLab-V3": {"result": null}, "Comodo": {"result": "UnclassifiedMalware"}, "TheHacker": {"result": null}, "F-Prot": {"result": null}, "Fortinet": {"result": "Android/Boxer.D"}, "TrendMicro-HouseCall": {"result": "TROJ_GEN.RCBH1GI"}, "SUPERAntiSpyware": {"result": null}, "VIPRE": {"result": "Trojan.AndroidOS.Boxer.d (v)"}, "VBA32": {"result": null}, "BitDefender": {"result": "Android.Trojan.FakeInst.AS"}, "TrendMicro": {"result": "AndroidOS_FakeInst.D"}, "DrWeb": {"result": "Android.SmsSend.395"}, "ByteHero": {"result": null}, "Symantec": {"result": "Trojan.Gen.2"}, "Antiy-AVL": {"result": "Trojan/AndroidOS.FakeInst"}, "nProtect": {"result": null}, "Norman": {"result": null}, "McAfee": {"result": null}, "Emsisoft": {"result": "Trojan.AndroidOS.BoxerSms!IK"}, "ClamAV": {"result": null}, "F-Secure": {"result": "Trojan:Android/Boxer.C"}, "Avast": {"result": "Android:FakeInst-AB [Trj]"}, "Microsoft": {"result": "Program:AndroidOS/BoxerSms.D"}, "Commtouch": {"result": null}, "K7AntiVirus": {"result": null}, "Kaspersky": {"result": "HEUR:Trojan-SMS.AndroidOS.FakeInst.a"}, "ViRobot": {"result": null}, "GData": {"result": "Android.Trojan.FakeInst.AS"}, "Ikarus": {"result": "Trojan.AndroidOS.BoxerSms"}, "Sophos": {"result": "Andr/Boxer-D"}, "AntiVir": {"result": "Android/BoxerSms.D"}, "AVG": {"result": null}, "PCTools": {"result": "Trojan.Gen"}, "ESET-NOD32": {"result": "Android/TrojanSMS.Boxer.AQ.Gen"}, "Jiangmin": {"result": "Backdoor/AndroidOS.dfx"}, "VirusBuster": {"result": null}, "McAfee-GW-Edition": {"result": null}, "eSafe": {"result": null}, "Rising": {"result": null}, "Panda": {"result": null}}}, "added_timestamp": "2012-12-28T18:06:56+00:00", "md5": "e856b7a72f76cc6bafb1260d57f4cef5", "exif": {"FileSize": "468 kB", "FileType": "ZIP", "FileTypeExtension": "zip", "MIMEType": "application/zip", "ZipBitFlag": "0x0808", "ZipCRC": "0x4f4bafeb", "ZipCompressedSize": 967, "ZipCompression": "Deflated", "ZipFileName": "META-INF/MANIFEST.MF", "ZipModifyDate": "2012:07:16 20:15:11", "ZipRequiredVersion": 20, "ZipUncompressedSize": 3206}, "ssdeep": "12288:CkLkqkJk0kLk2kqkJkgknk2kVkckzkh0XFU61U6RU6eU6aqbbi5:tw1qLwJ1q/kJ+zYh011Reaui5", "sha512": "fde46c680881b145568f4d3d2a0498afcfe4e1f23a48b3e335101a2acf4cee59e0cca047d45f50d97a4b5dba7d040f8a9001a69b72a718587fa321f4f01ac74a", "sha384": "f430a68cc75f5d013f4397df539413d2c3816cc4808b1ba4d388d26914c78f437b9584a40ac85941702d3e8166bb28df", "size": 478799, "mimetype": "application/zip", "sha1": "ce15522db6d82935a4602f32cd3eaa8a760f09fe", "trid": {"0": "Android Package (73.9%)", "1": "Java Archive (20.4%)", "2": "ZIP compressed archive (5.6%)"}, "sha224": "8823978febe8f931cf7b1d77f2a0eded757a5215026c262fc5f267a3", "extension": "apk", "filetype": "Zip archive data, at least v2.0 to extract", "response": 1}