{"sha256": "31fa159f77d3404124bf169055cf1b3d97258af16214429f6c3d3838e2b1d90f", "md5": "f42215cd63e8831d84755880d940103b", "sha224": "40675670f19ae4ba6922604b7df04138d68ee8b20f74c1153459e121", "extension": "apk", "sha384": "1b2ea3c92469c2f5de5e8cb1f528547614f1b63557a821e4ab7110f711c73d0fd60807e6d7fd295bb2b270c71faf12ca", "sha512": "30ede40f1de70c4d505e3423736508a277d880c2117db0739c0feed7f90abef877b96c02c1037831b425c4a7ecb7854bcefe3daaefcd64f3b01fbe50b7393409", "sha1": "4994ae2ede62795b38d237eaa484ad6a04812388", "ssdeep": "768:SqnL5SnvIABCbxRaA+PektA+PYmH9A+PNAo0ZVs1dr0K1KGYOmE472v3zqFNzqFN:Fs2kzAojVAouFK4GTmRav3GnG+Gr9", "filetype": "Zip archive data, at least v2.0 to extract", "size": 61963, "trid": {"0": "Android Package (73.9%)", "1": "Java Archive (20.4%)", "2": "ZIP compressed archive (5.6%)"}, "mimetype": "application/zip", "exif": {"FileSize": "61 kB", "FileType": "ZIP", "FileTypeExtension": "zip", "MIMEType": "application/zip", "ZipBitFlag": "0x0008", "ZipCRC": "0x9ca56f19", "ZipCompressedSize": 641, "ZipCompression": "Deflated", "ZipFileName": "META-INF/MANIFEST.MF", "ZipModifyDate": "2012:01:07 00:09:26", "ZipRequiredVersion": 20, "ZipUncompressedSize": 1589}, "virustotal": {"permalink": "http://www.virustotal.com/file/31fa159f77d3404124bf169055cf1b3d97258af16214429f6c3d3838e2b1d90f/analysis/", "scan_date": "2012-01-10 22:05:16", "positives": 9, "total": 43, "scans": {"CAT-QuickHeal": {"result": ""}, "AhnLab-V3": {"result": ""}, "Comodo": {"result": "UnclassifiedMalware"}, "NOD32": {"result": "Android/TrojanSMS.FakeInst.K"}, "TheHacker": {"result": ""}, "F-Prot": {"result": ""}, "Fortinet": {"result": ""}, "TrendMicro-HouseCall": {"result": ""}, "SUPERAntiSpyware": {"result": ""}, "Prevx": {"result": ""}, "VIPRE": {"result": ""}, "VBA32": {"result": ""}, "BitDefender": {"result": ""}, "TrendMicro": {"result": ""}, "DrWeb": {"result": ""}, "ByteHero": {"result": ""}, "Sophos": {"result": ""}, "Symantec": {"result": ""}, "Antiy-AVL": {"result": ""}, "nProtect": {"result": ""}, "Norman": {"result": ""}, "McAfee": {"result": ""}, "Emsisoft": {"result": "Android.FakeInst!IK"}, "ClamAV": {"result": ""}, "F-Secure": {"result": "Trojan:Android/Fakeinst.D!mfb"}, "Avast": {"result": "Android:FakeInst-Q [Trj]"}, "Microsoft": {"result": "Trojan:AndroidOS/FakeInstSms.A"}, "Commtouch": {"result": ""}, "K7AntiVirus": {"result": ""}, "Kaspersky": {"result": "HEUR:Trojan-SMS.AndroidOS.FakeInst.a"}, "ViRobot": {"result": ""}, "GData": {"result": "Android:FakeInst-Q "}, "Ikarus": {"result": "Android.FakeInst"}, "eTrust-Vet": {"result": ""}, "AntiVir": {"result": ""}, "AVG": {"result": ""}, "PCTools": {"result": ""}, "Jiangmin": {"result": ""}, "VirusBuster": {"result": ""}, "McAfee-GW-Edition": {"result": ""}, "eSafe": {"result": ""}, "Rising": {"result": ""}, "Panda": {"result": ""}}}, "added_timestamp": "2012-11-05T00:34:25+00:00", "response": 1}